kp2genes/__init__.py
kp2genes/kp2genes.py
keggpathway2genes-0.0.3.dist-info/METADATA
keggpathway2genes-0.0.3.dist-info/WHEEL
keggpathway2genes-0.0.3.dist-info/entry_points.txt
keggpathway2genes-0.0.3.dist-info/top_level.txt
keggpathway2genes-0.0.3.dist-info/RECORD
