Metadata-Version: 2.1
Name: keggpathway2genes
Version: 0.0.3
Summary: A package to convert KEGG Pathway IDs to genes
Author: Pr (France) Dr. rer. nat. Vijay K. ULAGANATHAN
Author-email: 
Requires-Dist: argparse
Requires-Dist: bs4
Requires-Dist: requests
Requires-Dist: tqdm
